pymdmix_project/__init__.py
pymdmix_project/project.py
pymdmix_project-0.0.2.data/data/pymdmix/pymdmix_project.yml
pymdmix_project-0.0.2.dist-info/LICENSE
pymdmix_project-0.0.2.dist-info/METADATA
pymdmix_project-0.0.2.dist-info/WHEEL
pymdmix_project-0.0.2.dist-info/top_level.txt
pymdmix_project-0.0.2.dist-info/RECORD
